swimrankings/__init__.py
swimrankings/athlete.py
swimrankings/athletes.py
swimrankings/exceptions.py
swimrankings/models.py
swimrankings/parsers.py
swimrankings/reference_data.py
swimrankings/search.py
swimrankings/utils.py
swimrankings-0.1.1.dist-info/METADATA
swimrankings-0.1.1.dist-info/WHEEL
swimrankings-0.1.1.dist-info/licenses/LICENSE
swimrankings-0.1.1.dist-info/RECORD
