Metadata-Version: 2.4
Name: swimrankings
Version: 0.1.1
Summary: A modern Python library for interacting with swimrankings.net
Project-URL: Homepage, https://github.com/MauroDruwel/Swimrankings
Project-URL: Documentation, https://maurodruwel.be/Swimrankings/
Project-URL: Repository, https://github.com/MauroDruwel/Swimrankings
Project-URL: Issues, https://github.com/MauroDruwel/Swimrankings/issues
Author-email: Mauro Druwel <mauro.druwel@gmail.com>
License: MIT
License-File: LICENSE
Classifier: Development Status :: 3 - Alpha
Classifier: Intended Audience :: Developers
Classifier: License :: OSI Approved :: MIT License
Classifier: Programming Language :: Python :: 3
Classifier: Programming Language :: Python :: 3.8
Classifier: Programming Language :: Python :: 3.9
Classifier: Programming Language :: Python :: 3.10
Classifier: Programming Language :: Python :: 3.11
Classifier: Programming Language :: Python :: 3.12
Requires-Python: >=3.8
Requires-Dist: beautifulsoup4>=4.11.0
Requires-Dist: lxml>=4.9.0
Requires-Dist: requests>=2.28.0
Provides-Extra: dev
Requires-Dist: black>=23.0; extra == 'dev'
Requires-Dist: flake8>=6.0; extra == 'dev'
Requires-Dist: mypy>=1.0; extra == 'dev'
Requires-Dist: pytest-cov>=4.0; extra == 'dev'
Requires-Dist: pytest>=7.0; extra == 'dev'
